openmemory/__init__.py
openmemory/client.py
openmemory/main.py
openmemory/openai_handler.py
openmemory/trace.py
openmemory/ai/__init__.py
openmemory/ai/adapter.py
openmemory/ai/aws.py
openmemory/ai/gemini.py
openmemory/ai/mcp.py
openmemory/ai/ollama.py
openmemory/ai/openai.py
openmemory/ai/synthetic.py
openmemory/connectors/__init__.py
openmemory/connectors/agents.py
openmemory/connectors/base.py
openmemory/connectors/github.py
openmemory/connectors/google_drive.py
openmemory/connectors/google_sheets.py
openmemory/connectors/google_slides.py
openmemory/connectors/langchain.py
openmemory/connectors/notion.py
openmemory/connectors/onedrive.py
openmemory/connectors/web_crawler.py
openmemory/core/config.py
openmemory/core/constants.py
openmemory/core/db.py
openmemory/core/models.py
openmemory/core/types.py
openmemory/core/vector_store.py
openmemory/core/vector/__init__.py
openmemory/core/vector/postgres.py
openmemory/core/vector/valkey.py
openmemory/integrations/agents.py
openmemory/integrations/langchain.py
openmemory/memory/decay.py
openmemory/memory/embed.py
openmemory/memory/hsg.py
openmemory/memory/reflect.py
openmemory/memory/scoring.py
openmemory/memory/user_summary.py
openmemory/migrations/001_initial.sql
openmemory/migrations/__init__.py
openmemory/ops/compress.py
openmemory/ops/dynamics.py
openmemory/ops/extract.py
openmemory/ops/ingest.py
openmemory/server/api.py
openmemory/server/routes/__init__.py
openmemory/server/routes/health.py
openmemory/server/routes/memory.py
openmemory/server/routes/sources.py
openmemory/temporal_graph/__init__.py
openmemory/temporal_graph/query.py
openmemory/temporal_graph/store.py
openmemory/temporal_graph/timeline.py
openmemory/temporal_graph/types.py
openmemory/utils/chunking.py
openmemory/utils/keyword.py
openmemory/utils/text.py
openmemory/utils/vectors.py
openmemory_py-1.3.1.dist-info/METADATA
openmemory_py-1.3.1.dist-info/WHEEL
openmemory_py-1.3.1.dist-info/RECORD
