Metadata-Version: 2.4
Name: openmemory-py
Version: 1.3.1
Summary: OpenMemory Python SDK
Requires-Dist: beautifulsoup4>=4.0
Requires-Dist: fastapi
Requires-Dist: google-api-python-client>=2.0
Requires-Dist: google-auth>=2.0
Requires-Dist: httpx
Requires-Dist: mammoth>=1.6
Requires-Dist: markdownify>=0.11
Requires-Dist: msal>=1.0
Requires-Dist: notion-client>=2.0
Requires-Dist: numpy
Requires-Dist: openai>=1.0
Requires-Dist: pydantic
Requires-Dist: pygithub>=2.0
Requires-Dist: pypdf>=4.0
Requires-Dist: uvicorn
